danb/__init__.py
danb/utils.py
danb-0.0.4.dist-info/METADATA
danb-0.0.4.dist-info/WHEEL
danb-0.0.4.dist-info/top_level.txt
danb-0.0.4.dist-info/RECORD
